cyberdem/__init__.py
cyberdem/base/__init__.py
cyberdem/enumerations/__init__.py
cyberdem/filesystem/__init__.py
cyberdem/structures/__init__.py
cyberdem/widgets/__init__.py
cyberdem-0.0.7.dist-info/LICENSE.md
cyberdem-0.0.7.dist-info/METADATA
cyberdem-0.0.7.dist-info/WHEEL
cyberdem-0.0.7.dist-info/top_level.txt
cyberdem-0.0.7.dist-info/RECORD
