Metadata-Version: 2.1
Name: cyberdem
Version: 0.0.7
Summary: Cyber DEM SISO standard python helper package
Home-page: https://github.com/cmu-sei/cyberdem-python
Author: Carnegie Mellon University
Author-email: UNKNOWN
License: # CyberDEM Python License
